cosmoglobe/__init__.py
cosmoglobe/__main__.py
cosmoglobe/data/__init__.py
cosmoglobe/data/autoparams.json
cosmoglobe/data/mask_template_n256.fits
cosmoglobe/data/planck_cmap.dat
cosmoglobe/data/planck_log_cmap.dat
cosmoglobe/data/radio_catalog.dat
cosmoglobe/data/spdust2_cnm.dat
cosmoglobe/data/wmap_cmap.dat
cosmoglobe/fits/__init__.py
cosmoglobe/fits/click_fits.py
cosmoglobe/h5/__init__.py
cosmoglobe/h5/_alms.py
cosmoglobe/h5/_decorators.py
cosmoglobe/h5/_exceptions.py
cosmoglobe/h5/chain.py
cosmoglobe/h5/click_h5.py
cosmoglobe/interface/__init__.py
cosmoglobe/interface/ui.py
cosmoglobe/plot/__init__.py
cosmoglobe/plot/click_plotting.py
cosmoglobe/plot/gnomonic.py
cosmoglobe/plot/histogram.py
cosmoglobe/plot/plottools.py
cosmoglobe/plot/skymap.py
cosmoglobe/plot/spectrum.py
cosmoglobe/plot/temp_newvisufunc.py
cosmoglobe/plot/traceplot.py
cosmoglobe/release/Synchrotron_template_GHz_extended.txt
cosmoglobe/release/__init__.py
cosmoglobe/release/autoparams.json
cosmoglobe/release/commands.py
cosmoglobe/release/commands_fits.py
cosmoglobe/release/commands_hdf.py
cosmoglobe/release/commands_plotting.py
cosmoglobe/release/fitsformatter.py
cosmoglobe/release/planck_cmap.dat
cosmoglobe/release/planck_cmap_logscale.dat
cosmoglobe/release/plotter.py
cosmoglobe/release/spdust2_cnm.dat
cosmoglobe/release/spectrum.py
cosmoglobe/release/tools.py
cosmoglobe/release/wmap_cmap.dat
cosmoglobe/sky/__init__.py
cosmoglobe/sky/_bandpass.py
cosmoglobe/sky/_base_components.py
cosmoglobe/sky/_beam.py
cosmoglobe/sky/_chain_context.py
cosmoglobe/sky/_component_factory.py
cosmoglobe/sky/_constants.py
cosmoglobe/sky/_context_registry.py
cosmoglobe/sky/_exceptions.py
cosmoglobe/sky/_freq_range.py
cosmoglobe/sky/_intensity_derivatives.py
cosmoglobe/sky/_newcomps.py
cosmoglobe/sky/_units.py
cosmoglobe/sky/components/__init__.py
cosmoglobe/sky/components/_labels.py
cosmoglobe/sky/components/ame.py
cosmoglobe/sky/components/cmb.py
cosmoglobe/sky/components/dust.py
cosmoglobe-0.9.85.dist-info/LICENSE
cosmoglobe-0.9.85.dist-info/METADATA
cosmoglobe-0.9.85.dist-info/WHEEL
cosmoglobe-0.9.85.dist-info/entry_points.txt
cosmoglobe-0.9.85.dist-info/RECORD
