Metadata-Version: 2.1
Name: cosmoglobe
Version: 0.9.85
Summary: A Python package for interfacing the Cosmoglobe Sky Model with commander3 outputs for the purpose of producing astrophysical sky maps.
Home-page: https://github.com/Cosmoglobe/Cosmoglobe
License: GNU GPLv3
Author: Metin San
Author-email: metinisan@gmail.com
Maintainer: Metin San
Maintainer-email: metinisan@gmail.com
Requires-Python: >=3.9
Classifier: License :: Other/Proprietary License
Classifier: Programming Language :: Python :: 3
Classifier: Programming Language :: Python :: 3.9
Classifier: Programming Language :: Python :: 3.10
Classifier: Programming Language :: Python :: 3.11
Classifier: Programming Language :: Python :: 3.12
Requires-Dist: astropy (>=5.2.0)
Requires-Dist: click (>=8.1.7,<9.0.0)
Requires-Dist: cmasher (>=1.8.0,<2.0.0) ; python_version >= "3.9" and python_version < "4"
Requires-Dist: h5py (>=3.0.0)
Requires-Dist: healpy (>=1.15.2,<2.0.0)
Requires-Dist: numba (>=0.59.1,<0.60.0)
Requires-Dist: numpy (>=1.26.4,<2.0.0)
Requires-Dist: rich (>=13.5.3,<14.0.0)
Requires-Dist: scipy (>=1.13.0,<2.0.0)
Requires-Dist: setuptools (>=68.2.2,<69.0.0)
Requires-Dist: tqdm (>=4.62.3,<5.0.0)
Project-URL: Documentation, https://cosmoglobe.readthedocs.io
Project-URL: Repository, https://github.com/Cosmoglobe/Cosmoglobe
